alasco/__init__.py
alasco/client.py
alasco/data_fetcher.py
alasco/data_transformer.py
alasco/data_updater.py
alasco/document_downloader.py
alasco/document_uploader.py
alasco/utils.py
alasco-0.0.9.dist-info/METADATA
alasco-0.0.9.dist-info/WHEEL
alasco-0.0.9.dist-info/licenses/LICENSE
alasco-0.0.9.dist-info/RECORD
