Metadata-Version: 2.4
Name: alasco
Version: 0.0.9
Summary: A SDK to facilitate the interaction with the Alasco API.
Project-URL: Homepage, https://github.com/sylvainHellin/Alasco
Project-URL: Issues, https://github.com/sylvainHellin/Alasco/issues
Author-email: Sylvain Hellin <hellinsylvain@gmail.com>
License-File: LICENSE
Classifier: License :: OSI Approved :: MIT License
Classifier: Operating System :: OS Independent
Classifier: Programming Language :: Python :: 3
Requires-Python: >=3.12
Requires-Dist: pandas
Requires-Dist: pydantic>=2.11.4
Requires-Dist: python-dotenv>=1.1.0
Requires-Dist: requests
